{
  "ID": "85",
  "post_author": "130",
  "post_date": "2005-03-16 01:57:44",
  "post_date_gmt": "2005-03-16 06:57:44",
  "post_content": "Midterms, computer stuff... fill in details later",
  "post_title": "Been forgetting..",
  "post_category": "0",
  "post_excerpt": "",
  "post_lat": null,
  "post_lon": null,
  "post_status": "publish",
  "comment_status": "open",
  "ping_status": "open",
  "post_password": "",
  "post_name": "been-forgetting",
  "to_ping": "",
  "pinged": "",
  "post_modified": "2005-03-16 01:57:44",
  "post_modified_gmt": "2005-03-16 06:57:44",
  "post_content_filtered": "",
  "post_parent": "0",
  "guid": "http://www.timmfin.net/?p=85",
  "menu_order": "0",
  "post_type": "post",
  "post_mime_type": "",
  "comment_count": "0"
}
